{
  "$schema": "https://developer.microsoft.com/json-schemas/fabric/item/report/definition/bookmark/2.1.0/schema.json",
  "displayName": "Nav_FiltreEpuise",
  "name": "a5f1d2c3b4e50617283a",
  "options": {
    "targetVisualNames": []
  },
  "explorationState": {
    "version": "1.3",
    "activeSection": "54f9d470ac60b85b18da",
    "sections": {
      "54f9d470ac60b85b18da": {
        "filters": {
          "byExpr": [
            {
              "name": "e5f1d2c3b4e506172836",
              "type": "Categorical",
              "filter": {
                "Version": 2,
                "From": [
                  {
                    "Name": "t",
                    "Entity": "T_Produits_Dim",
                    "Type": 0
                  }
                ],
                "Where": [
                  {
                    "Condition": {
                      "In": {
                        "Expressions": [
                          {
                            "Column": {
                              "Expression": {
                                "SourceRef": {
                                  "Source": "t"
                                }
                              },
                              "Property": "NiveauRisqueStock"
                            }
                          }
                        ],
                        "Values": [
                          [
                            {
                              "Literal": {
                                "Value": "'Stock epuise'"
                              }
                            }
                          ]
                        ]
                      }
                    }
                  }
                ]
              },
              "expression": {
                "Column": {
                  "Expression": {
                    "SourceRef": {
                      "Entity": "T_Produits_Dim"
                    }
                  },
                  "Property": "NiveauRisqueStock"
                }
              },
              "howCreated": 1
            }
          ]
        },
        "visualContainers": {
          "ux_risk_quickfilter_p2": {
            "filters": {
              "byExpr": [
                {
                  "name": "b5f1d2c3b4e50617283a",
                  "type": "Categorical",
                  "filter": {
                    "Version": 2,
                    "From": [
                      {
                        "Name": "t",
                        "Entity": "T_Produits_Dim",
                        "Type": 0
                      }
                    ],
                    "Where": [
                      {
                        "Condition": {
                          "In": {
                            "Expressions": [
                              {
                                "Column": {
                                  "Expression": {
                                    "SourceRef": {
                                      "Source": "t"
                                    }
                                  },
                                  "Property": "NiveauRisqueStock"
                                }
                              }
                            ],
                            "Values": [
                              [
                                {
                                  "Literal": {
                                    "Value": "'Stock epuise'"
                                  }
                                }
                              ]
                            ]
                          }
                        }
                      }
                    ]
                  },
                  "expression": {
                    "Column": {
                      "Expression": {
                        "SourceRef": {
                          "Entity": "T_Produits_Dim"
                        }
                      },
                      "Property": "NiveauRisqueStock"
                    }
                  },
                  "howCreated": 0
                }
              ]
            },
            "singleVisual": {
              "visualType": "slicer",
              "objects": {
                "merge": {
                  "data": [
                    {
                      "properties": {
                        "mode": {
                          "expr": {
                            "Literal": {
                              "Value": "'Basic'"
                            }
                          }
                        }
                      }
                    }
                  ]
                }
              },
              "activeProjections": {
                "Values": [
                  {
                    "Column": {
                      "Expression": {
                        "SourceRef": {
                          "Entity": "T_Produits_Dim"
                        }
                      },
                      "Property": "NiveauRisqueStock"
                    }
                  }
                ]
              }
            }
          }
        }
      }
    },
    "objects": {
      "merge": {
        "outspacePane": [
          {
            "properties": {
              "expanded": {
                "expr": {
                  "Literal": {
                    "Value": "true"
                  }
                }
              }
            }
          }
        ]
      }
    }
  }
}