{
    "$schema":  "https://developer.microsoft.com/json-schemas/fabric/item/report/definition/visualContainer/2.6.0/schema.json",
    "name":  "p3-drill-instruction",
    "position":  {
                     "x":  770,
                     "y":  296,
                     "z":  9000,
                     "height":  34,
                     "width":  900,
                     "tabOrder":  10000
                 },
    "visual":  {
                   "visualType":  "textbox",
                   "objects":  {
                                   "general":  [
                                                   {
                                                       "properties":  {
                                                                          "paragraphs":  [
                                                                                             {
                                                                                                 "textRuns":  [
                                                                                                                  {
                                                                                                                      "value":  "Selectionnez une ligne puis cliquez sur Voir detail (ou clic droit \u003e Extraire \u003e Detail Utilisateur)",
                                                                                                                      "textStyle":  {
                                                                                                                                        "fontFamily":  "Segoe UI",
                                                                                                                                        "fontSize":  "10pt",
                                                                                                                                        "color":  "#4B5563"
                                                                                                                                    }
                                                                                                                  }
                                                                                                              ]
                                                                                             }
                                                                                         ]
                                                                      }
                                                   }
                                               ]
                               },
                   "visualContainerObjects":  {
                                                  "background":  [
                                                                     {
                                                                         "properties":  {
                                                                                            "show":  {
                                                                                                         "expr":  {
                                                                                                                      "Literal":  {
                                                                                                                                      "Value":  "true"
                                                                                                                                  }
                                                                                                                  }
                                                                                                     },
                                                                                            "color":  {
                                                                                                          "solid":  {
                                                                                                                        "color":  {
                                                                                                                                      "expr":  {
                                                                                                                                                   "Literal":  {
                                                                                                                                                                   "Value":  "\u0027#F9FAFB\u0027"
                                                                                                                                                               }
                                                                                                                                               }
                                                                                                                                  }
                                                                                                                    }
                                                                                                      },
                                                                                            "transparency":  {
                                                                                                                 "expr":  {
                                                                                                                              "Literal":  {
                                                                                                                                              "Value":  "0D"
                                                                                                                                          }
                                                                                                                          }
                                                                                                             }
                                                                                        }
                                                                     }
                                                                 ],
                                                  "border":  [
                                                                 {
                                                                     "properties":  {
                                                                                        "show":  {
                                                                                                     "expr":  {
                                                                                                                  "Literal":  {
                                                                                                                                  "Value":  "true"
                                                                                                                              }
                                                                                                              }
                                                                                                 },
                                                                                        "color":  {
                                                                                                      "solid":  {
                                                                                                                    "color":  {
                                                                                                                                  "expr":  {
                                                                                                                                               "Literal":  {
                                                                                                                                                               "Value":  "\u0027#E5E7EB\u0027"
                                                                                                                                                           }
                                                                                                                                           }
                                                                                                                              }
                                                                                                                }
                                                                                                  },
                                                                                        "radius":  {
                                                                                                       "expr":  {
                                                                                                                    "Literal":  {
                                                                                                                                    "Value":  "8D"
                                                                                                                                }
                                                                                                                }
                                                                                                   },
                                                                                        "width":  {
                                                                                                      "expr":  {
                                                                                                                   "Literal":  {
                                                                                                                                   "Value":  "1D"
                                                                                                                               }
                                                                                                               }
                                                                                                  }
                                                                                    }
                                                                 }
                                                             ]
                                              }
               }
}